odoo/addons/intrastat_base/README.rst
odoo/addons/intrastat_base/__init__.py
odoo/addons/intrastat_base/__manifest__.py
odoo/addons/intrastat_base/data/country_data.xml
odoo/addons/intrastat_base/demo/intrastat_demo.xml
odoo/addons/intrastat_base/i18n/es.po
odoo/addons/intrastat_base/i18n/fr.po
odoo/addons/intrastat_base/i18n/intrastat_base.pot
odoo/addons/intrastat_base/migrations/13.0.1.1.1/post-migration.py
odoo/addons/intrastat_base/models/__init__.py
odoo/addons/intrastat_base/models/account_tax.py
odoo/addons/intrastat_base/models/intrastat_common.py
odoo/addons/intrastat_base/models/product_template.py
odoo/addons/intrastat_base/models/res_company.py
odoo/addons/intrastat_base/models/res_config_settings.py
odoo/addons/intrastat_base/models/res_country.py
odoo/addons/intrastat_base/models/res_partner.py
odoo/addons/intrastat_base/readme/CONTRIBUTORS.rst
odoo/addons/intrastat_base/readme/DESCRIPTION.rst
odoo/addons/intrastat_base/readme/INSTALL.rst
odoo/addons/intrastat_base/readme/USAGE.rst
odoo/addons/intrastat_base/static/description/icon.png
odoo/addons/intrastat_base/static/description/index.html
odoo/addons/intrastat_base/tests/__init__.py
odoo/addons/intrastat_base/tests/common.py
odoo/addons/intrastat_base/tests/test_all.py
odoo/addons/intrastat_base/views/account_tax.xml
odoo/addons/intrastat_base/views/intrastat.xml
odoo/addons/intrastat_base/views/product_template.xml
odoo/addons/intrastat_base/views/res_config_settings.xml
odoo/addons/intrastat_base/views/res_country.xml
odoo/addons/intrastat_base/views/res_partner.xml
odoo13_addon_intrastat_base-13.0.2.0.0.dist-info/METADATA
odoo13_addon_intrastat_base-13.0.2.0.0.dist-info/WHEEL
odoo13_addon_intrastat_base-13.0.2.0.0.dist-info/top_level.txt
odoo13_addon_intrastat_base-13.0.2.0.0.dist-info/RECORD
